Metadata-Version: 2.1
Name: oneNeuron-pypi-Avinash905
Version: 0.0.2
Summary: it is an implementation of perceptron
Home-page: https://github.com/Avinash905/oneNeuron_pypi
Author: Avinash905
Author-email: avinash.90527@gmail.com
License: UNKNOWN
Project-URL: Bug Tracker, https://github.com/pypa/Avinash905/oneNeuron_pypi
Platform: UNKNOWN
Classifier: Programming Language :: Python :: 3
Classifier: License :: OSI Approved :: MIT License
Classifier: Operating System :: OS Independent
Requires-Python: >=3.7
License-File: LICENSE
Requires-Dist: numpy
Requires-Dist: tqdm
